ljainlib/__init__.py
ljainlib/file_ops/__init__.py
ljainlib/file_ops/reader.py
ljainlib/math_ops/__init__.py
ljainlib/math_ops/arithmetic.py
ljainlib/string_ops/__init__.py
ljainlib/string_ops/formatter.py
ljainlib-0.1.0.dist-info/licenses/LICENSE
ljainlib-0.1.0.dist-info/METADATA
ljainlib-0.1.0.dist-info/WHEEL
ljainlib-0.1.0.dist-info/top_level.txt
ljainlib-0.1.0.dist-info/RECORD
